request/__init__.py
request/admin.py
request/apps.py
request/managers.py
request/middleware.py
request/models.py
request/plugins.py
request/router.py
request/settings.py
request/traffic.py
request/utils.py
request/locale/de/LC_MESSAGES/django.mo
request/locale/de/LC_MESSAGES/django.po
request/locale/en/LC_MESSAGES/django.po
request/locale/es/LC_MESSAGES/django.mo
request/locale/es/LC_MESSAGES/django.po
request/locale/fr/LC_MESSAGES/django.mo
request/locale/fr/LC_MESSAGES/django.po
request/management/__init__.py
request/management/commands/__init__.py
request/management/commands/purgerequests.py
request/migrations/0001_initial.py
request/migrations/0002_alter_request_ip.py
request/migrations/0003_auto_20160331_1430.py
request/migrations/0004_alter_time_timezone_default.py
request/migrations/0005_alter_request_user.py
request/migrations/0006_alter_request_method_default.py
request/migrations/0007_alter_request_is_ajax.py
request/migrations/0008_alter_request_response_choices.py
request/migrations/__init__.py
request/static/request/js/excanvas.min.js
request/static/request/js/jquery-1.4.2.min.js
request/static/request/js/jquery.flot.js
request/static/request/js/jquery.timeago.js
request/static/request/js/request.js
request/templates/admin/request/app_index.html
request/templates/admin/request/request/change_list.html
request/templates/admin/request/request/overview.html
request/templates/request/plugins/activeusers.html
request/templates/request/plugins/base.html
request/templates/request/plugins/latestrequests.html
request/templates/request/plugins/table.html
request/templates/request/plugins/topbrowsers.html
request/templates/request/plugins/toppaths.html
request/templates/request/plugins/topreferrers.html
request/templates/request/plugins/topsearchphrases.html
request/templates/request/plugins/trafficinformation.html
request/templatetags/__init__.py
request/templatetags/request_admin.py
request/templatetags/request_tag.py
django_request-1.6.3.dist-info/LICENSE
django_request-1.6.3.dist-info/METADATA
django_request-1.6.3.dist-info/WHEEL
django_request-1.6.3.dist-info/top_level.txt
django_request-1.6.3.dist-info/RECORD
