Metadata-Version: 2.1
Name: django-request
Version: 1.6.3
Summary: django-request is a statistics module for django. It stores requests in a database for admins to see, it can also be used to get statistics on who is online etc.
Home-page: https://django-request.readthedocs.io/en/latest/
Author: Kyle Fuller
Author-email: kyle@fuller.li
Maintainer: Mariusz Felisiak
Maintainer-email: felisiak.mariusz@gmail.com
License: BSD
Download-URL: https://pypi.org/project/django-request/
Platform: UNKNOWN
Classifier: Development Status :: 5 - Production/Stable
Classifier: Environment :: Web Environment
Classifier: Framework :: Django
Classifier: Framework :: Django :: 2.2
Classifier: Framework :: Django :: 3.2
Classifier: Framework :: Django :: 4.0
Classifier: Framework :: Django :: 4.1
Classifier: Framework :: Django :: 4.2
Classifier: Intended Audience :: Developers
Classifier: License :: OSI Approved :: BSD License
Classifier: Operating System :: OS Independent
Classifier: Programming Language :: Python
Classifier: Programming Language :: Python :: 3
Classifier: Programming Language :: Python :: 3.6
Classifier: Programming Language :: Python :: 3.7
Classifier: Programming Language :: Python :: 3.8
Classifier: Programming Language :: Python :: 3.9
Classifier: Programming Language :: Python :: 3.10
Classifier: Programming Language :: Python :: 3.11
License-File: LICENSE
